dohome/__init__.py
dohome/api/__init__.py
dohome/api/client.py
dohome/api/constants.py
dohome/api/dgram_client.py
dohome/api/hardware.py
dohome/api/message.py
dohome/api/transport.py
dohome/api/types/__init__.py
dohome/api/types/common.py
dohome/api/types/device.py
dohome/api/types/dgram.py
dohome/api/types/light.py
dohome/api/types/wifi.py
dohome/cli/__init__.py
dohome/cli/batch.py
dohome/cli/describe.py
dohome/cli/discover.py
dohome/cli/light.py
dohome/color/__init__.py
dohome/color/int.py
dohome/color/light_state.py
dohome/color/rgb.py
dohome/color/temperature.py
dohome/exc/__init__.py
dohome/exc/base.py
dohome/exc/request.py
dohome/exc/response.py
dohome/socket/__init__.py
dohome/socket/tcp_stream.py
dohome/socket/udp_broadcast.py
dohome/socket/utils.py
dohome_api-1.1.0.dist-info/LICENSE
dohome_api-1.1.0.dist-info/METADATA
dohome_api-1.1.0.dist-info/WHEEL
dohome_api-1.1.0.dist-info/entry_points.txt
dohome_api-1.1.0.dist-info/top_level.txt
dohome_api-1.1.0.dist-info/RECORD
