Metadata-Version: 2.2
Name: dohome_api
Version: 1.1.0
Summary: Library for controlling DoIT protocol lights
Author-email: Mikhael Khrustik <misha@myrt.co>
License: MIT
Keywords: doit,reverse-engineering,iot
Classifier: Programming Language :: Python :: 3
Classifier: License :: OSI Approved :: MIT License
Requires-Python: >=3.12
License-File: LICENSE
Requires-Dist: aiodatagram==0.0.2
Requires-Dist: arrrgs>=3.0.0
